Metadata-Version: 1.1
Name: webpurify-cli
Version: 1.0.0
Summary: 
